pymujoco.cpython-36m-x86_64-linux-gnu.so
pymujoco-0.0.4.dist-info/WHEEL
pymujoco-0.0.4.dist-info/RECORD
pymujoco-0.0.4.dist-info/METADATA
pymujoco-0.0.4.dist-info/top_level.txt
